MultinetPy/__init__.py
MultinetPy/graph_mng.py
MultinetPy/multinetpy.py
MultinetPy/multinetx/__init__.py
MultinetPy/multinetx/core/__init__.py
MultinetPy/multinetx/core/draw.py
MultinetPy/multinetx/core/exceptions.py
MultinetPy/multinetx/core/multilayer.py
MultinetPy/multinetx/core/utilities.py
multinetpy-0.1.2.dist-info/LICENSE
multinetpy-0.1.2.dist-info/METADATA
multinetpy-0.1.2.dist-info/WHEEL
multinetpy-0.1.2.dist-info/top_level.txt
multinetpy-0.1.2.dist-info/RECORD
