Metadata-Version: 2.1
Name: multinetpy
Version: 0.1.2
Home-page: 
Author: MultineyPy
Author-email: 
License: GNU License
License-File: LICENSE
Requires-Dist: contourpy==1.3.1
Requires-Dist: cycler==0.12.1
Requires-Dist: fonttools==4.55.0
Requires-Dist: kiwisolver==1.4.7
Requires-Dist: matplotlib==3.9.3
Requires-Dist: networkx==3.4.2
Requires-Dist: numpy==2.1.3
Requires-Dist: packaging==24.2
Requires-Dist: pandas==2.2.3
Requires-Dist: pillow==11.0.0
Requires-Dist: pyparsing==3.2.0
Requires-Dist: python-dateutil==2.9.0.post0
Requires-Dist: pytz==2024.2
Requires-Dist: scipy==1.14.1
Requires-Dist: seaborn==0.13.2
Requires-Dist: six==1.16.0
Requires-Dist: tzdata==2024.2
